auto_batch_pull/__init__.py
auto_batch_pull/main.py
auto_batch_pull-0.1.0.dist-info/LICENSE
auto_batch_pull-0.1.0.dist-info/METADATA
auto_batch_pull-0.1.0.dist-info/WHEEL
auto_batch_pull-0.1.0.dist-info/entry_points.txt
auto_batch_pull-0.1.0.dist-info/top_level.txt
auto_batch_pull-0.1.0.dist-info/RECORD
