Metadata-Version: 2.1
Name: auto-batch-pull
Version: 0.1.0
Summary: Automatically batch execute `git pull` command on all primary folders under the specified directory to update the repository to the latest version
Author: Guofeng Yi
Author-email: mark.yi@foxmail.com
License: Apache License 2.0
Requires-Python: >=3.6
License-File: LICENSE
